xhealpixify/__init__.py
xhealpixify/_healpy.py
xhealpixify/conversions.py
xhealpixify/grid.py
xhealpixify/operations.py
xhealpixify/regridder.py
xhealpixify/utils.py
xhealpixify/interpolation/bilinear.py
xhealpixify/interpolation/mask.py
xhealpixify-2025.3.3.dist-info/licenses/LICENSE
xhealpixify-2025.3.3.dist-info/METADATA
xhealpixify-2025.3.3.dist-info/WHEEL
xhealpixify-2025.3.3.dist-info/top_level.txt
xhealpixify-2025.3.3.dist-info/RECORD
