Metadata-Version: 2.4
Name: xhealpixify
Version: 2025.3.3
Summary: Tool for converting latitude/longitude data into HEALPix grids.
License: MIT
Requires-Python: >=3.10
License-File: LICENSE
Requires-Dist: xarray>=2023.11.0
Requires-Dist: healpy
Requires-Dist: sparse
Requires-Dist: opt_einsum
Requires-Dist: numba
Requires-Dist: numpy
Requires-Dist: sparse
Requires-Dist: scikit-learn
Requires-Dist: opt_einsum
Requires-Dist: cdshealpix
Requires-Dist: astropy
Requires-Dist: shapely
Requires-Dist: dask
Dynamic: license-file
